pycribbage/__init__.py
pycribbage/__main__.py
pycribbage/cribbage_game.py
pycribbage/cribbage_tools.py
pycribbage/deck_tools.py
pycribbage/discard_methods.py
pycribbage/player.py
pycribbage/scorer.py
pycribbage/the_play_methods.py
pycribbage-1.0.0.dist-info/LICENSE
pycribbage-1.0.0.dist-info/METADATA
pycribbage-1.0.0.dist-info/WHEEL
pycribbage-1.0.0.dist-info/entry_points.txt
pycribbage-1.0.0.dist-info/top_level.txt
pycribbage-1.0.0.dist-info/RECORD
