Metadata-Version: 2.1
Name: pycribbage
Version: 1.0.0
Summary: A Python application to play the card game cribbage
Author-email: John Otter <jjotter26@gmail.com>
License: MIT License
Project-URL: Homepage, https://github.com/jotter91/PythonCribbage
Keywords: cribbage
Requires-Python: >=3.8
License-File: LICENSE
Provides-Extra: dev
Requires-Dist: pytest ; extra == 'dev'
